botobuddy/apigw.py
botobuddy/auth.py
botobuddy/awslambda.py
botobuddy/cli.py
botobuddy/common.py
botobuddy/dynamo.py
botobuddy/logger.py
botobuddy/route53.py
botobuddy/s3.py
botobuddy/sagemaker.py
botobuddy/secman.py
botobuddy/utils.py
botobuddy-0.5.1.dist-info/licenses/LICENSE
botobuddy-0.5.1.dist-info/METADATA
botobuddy-0.5.1.dist-info/WHEEL
botobuddy-0.5.1.dist-info/entry_points.txt
botobuddy-0.5.1.dist-info/top_level.txt
botobuddy-0.5.1.dist-info/RECORD
