Metadata-Version: 2.4
Name: botobuddy
Version: 0.5.1
Summary: A Collection of Extension Functions Based on Boto3
Author-email: Boris Resnick <boris.resnick@gmail.com>
Project-URL: Homepage, https://github.com/scartill/botobuddy
Project-URL: Changelog, https://github.com/scartill/botobuddy/blob/main/CHANGELOG.md
Requires-Python: >=3.12
License-File: LICENSE
Requires-Dist: boto3>=1.38.15
Requires-Dist: click>=8.1.0
Requires-Dist: python-benedict[s3,toml,yaml]>=0.34.1
Requires-Dist: randomname>=0.2.1
Requires-Dist: rich>=13.0.0
Requires-Dist: types-boto3[apigateway,cloudformation,cognito-idp,essential,route53,sagemaker,secretsmanager,sts]>=1.38.35
Dynamic: license-file
